arviz_stats/__init__.py
arviz_stats/_version.py
arviz_stats/accessors.py
arviz_stats/bayes_factor.py
arviz_stats/ecdf_utils.py
arviz_stats/helper_stats.py
arviz_stats/manipulation.py
arviz_stats/metrics.py
arviz_stats/psense.py
arviz_stats/py.typed
arviz_stats/sampling_diagnostics.py
arviz_stats/summary.py
arviz_stats/survival.py
arviz_stats/utils.py
arviz_stats/validate.py
arviz_stats/visualization.py
arviz_stats/base/__init__.py
arviz_stats/base/array.py
arviz_stats/base/core.py
arviz_stats/base/dataarray.py
arviz_stats/base/density.py
arviz_stats/base/diagnostics.py
arviz_stats/base/stats_utils.py
arviz_stats/loo/__init__.py
arviz_stats/loo/compare.py
arviz_stats/loo/helper_loo.py
arviz_stats/loo/helper_loo_kfold.py
arviz_stats/loo/loo.py
arviz_stats/loo/loo_approximate_posterior.py
arviz_stats/loo/loo_expectations.py
arviz_stats/loo/loo_kfold.py
arviz_stats/loo/loo_moment_match.py
arviz_stats/loo/loo_pit.py
arviz_stats/loo/loo_score.py
arviz_stats/loo/loo_subsample.py
arviz_stats/loo/reloo.py
arviz_stats/loo/wrapper.py
arviz_stats/numba/__init__.py
arviz_stats/numba/array.py
arviz_stats/numba/dataarray.py
arviz_stats/numba/diagnostics.py
arviz_stats/numba/intervals.py
arviz_stats-0.7.0.dist-info/licenses/LICENSE
arviz_stats-0.7.0.dist-info/WHEEL
arviz_stats-0.7.0.dist-info/METADATA
arviz_stats-0.7.0.dist-info/RECORD
